{
    "font-name": "VideoJS",
    "root-dir": "./node_modules/material-design-icons/",
    "icons": [{
	"name": "play",
	"svg": "play.svg",
	"root-dir": "./custom-icons/adilo/"
    },{
	"name": "big-play",
	"svg": "big_play_button.svg",
	"root-dir": "./custom-icons/adilo/"
    }, {
	"name": "play-circle",
	"svg": "av/svg/production/ic_play_circle_outline_48px.svg"
    }, {
	"name": "pause",
	"svg": "pause.svg",
	"root-dir": "./custom-icons/adilo/"
    }, {
	"name": "volume-mute",
	"svg": "volume_muted.svg",
	"root-dir": "./custom-icons/adilo/"
    }, {
	"name": "volume-low",
	"svg": "volume_low.svg",
	"root-dir": "./custom-icons/adilo/"
    }, {
	"name": "volume-mid",
	"svg": "volume_mid.svg",
	"root-dir": "./custom-icons/adilo/"
    }, {
	"name": "volume-high",
	"svg": "volume_highest.svg",
	"root-dir": "./custom-icons/adilo/"
    }, {
	"name": "fullscreen-enter", 
	"svg": "fullscreen.svg",    
	"root-dir": "./custom-icons/adilo/"
    }, {
	"name": "fullscreen-exit",
	"svg": "minimize.svg",
	"root-dir": "./custom-icons/adilo/"
    }, {
	"name": "square",
	"svg": "image/svg/production/ic_crop_square_48px.svg"
    }, {
	"name": "spinner",
	"svg": "image/svg/production/ic_camera_48px.svg"
    }, {
	"name": "subtitles",
	"svg": "av/svg/production/ic_subtitles_48px.svg"
    }, {
	"name": "captions",
	"svg": "av/svg/production/ic_closed_caption_48px.svg"
    }, {
	"name": "chapters",
	"svg": "action/svg/production/ic_list_48px.svg"
    }, {
	"name": "share",
	"svg": "social/svg/production/ic_share_48px.svg"
    }, {
	"name": "cog",
	"svg": "settings.svg",
	"root-dir": "./custom-icons/adilo/"
    }, {
	"name": "circle",
	"svg": "image/svg/production/ic_brightness_1_48px.svg"
    }, {
	"name": "circle-outline",
	"svg": "image/svg/production/ic_panorama_fish_eye_48px.svg"
    }, {
	"name": "circle-inner-circle",
	"svg": "image/svg/production/ic_adjust_48px.svg"
    }, {
	"name": "hd",
	"svg": "av/svg/production/ic_hd_24px.svg"
    }, {
	"name": "cancel",
	"svg": "navigation/svg/production/ic_cancel_48px.svg"
    }, {
	"name": "replay",
	"svg": "replay.svg",
	"root-dir": "./custom-icons/adilo/"
    }, {
	"name": "audio-description",
	"svg": "audio-description.svg",
	"root-dir": "./custom-icons/"
    }, {
	"name": "audio",
	"svg": "hardware/svg/production/ic_headset_48px.svg"
    }, {
	"name": "video_share",
	"svg": "share.svg",
	"root-dir": "./custom-icons/adilo/"
    }, {
	"name": "next-item",
	"svg": "av/svg/production/ic_skip_next_48px.svg"
    }, {
	"name": "previous-item",
	"svg": "av/svg/production/ic_skip_previous_48px.svg"
    }, {
	"name": "adilo-logo",
	"svg": "logo.svg",
	"root-dir": "./custom-icons/adilo/"
    }]
}
